scraibe/__init__.py
scraibe/_version.py
scraibe/audio.py
scraibe/autotranscript.py
scraibe/cli.py
scraibe/diarisation.py
scraibe/hallucinations.py
scraibe/misc.py
scraibe/transcriber.py
scraibe/transcript_exporter.py
scraibe-0.3.0.dist-info/LICENSE
scraibe-0.3.0.dist-info/METADATA
scraibe-0.3.0.dist-info/WHEEL
scraibe-0.3.0.dist-info/entry_points.txt
scraibe-0.3.0.dist-info/RECORD
