Metadata-Version: 2.1
Name: scraibe
Version: 0.3.0
Summary: Transcription tool for audio files based on Whisper and Pyannote
Home-page: https://github.com/JSchmie/ScAIbe
License: GPL-3.0-or-later
Keywords: transcription,audio,whisper,pyannote,speech-to-text,speech-recognition
Author: Schmieder, Jacob
Author-email: jacob.schmieder@dbfz.de
Requires-Python: >=3.9,<4.0
Classifier: Development Status :: 4 - Beta
Classifier: Environment :: GPU :: NVIDIA CUDA :: 12 :: 12.1
Classifier: Intended Audience :: Developers
Classifier: License :: OSI Approved :: GNU General Public License v3 (GPLv3)
Classifier: License :: OSI Approved :: GNU General Public License v3 or later (GPLv3+)
Classifier: Programming Language :: Python :: 3
Classifier: Programming Language :: Python :: 3.9
Classifier: Programming Language :: Python :: 3.10
Classifier: Programming Language :: Python :: 3.11
Classifier: Programming Language :: Python :: 3.12
Classifier: Programming Language :: Python :: 3.13
Classifier: Programming Language :: Python :: 3.8
Classifier: Topic :: Scientific/Engineering :: Artificial Intelligence
Provides-Extra: app
Requires-Dist: faster-whisper (>=1.0.3,<2.0.0)
Requires-Dist: numpy (>=1.26.4,<2.0.0)
Requires-Dist: openai-whisper (>=20231117,<20240931)
Requires-Dist: pyannote.audio (>=3.3.1,<4.0.0)
Requires-Dist: torch (>=2.1.2,<3.0.0)
Requires-Dist: tqdm (>=4.66.5,<5.0.0)
Project-URL: Documentation, https://jschmie.github.io/ScrAIbe/
Project-URL: Repository, https://github.com/JSchmie/ScAIbe
